aud.cpython-311-darwin.so
audaspace.dylibs/libsamplerate.0.2.2.dylib
audaspace.dylibs/libaudaspace.1.8.dylib
audaspace.dylibs/libfftw3f.3.dylib
audaspace.dylibs/librubberband.3.dylib
audaspace-1.8.0.dist-info/RECORD
audaspace-1.8.0.dist-info/WHEEL
audaspace-1.8.0.dist-info/top_level.txt
audaspace-1.8.0.dist-info/METADATA
