Metadata-Version: 2.4
Name: audaspace
Version: 1.8.0
Summary: Audaspace is a high level audio library.
Home-page: https://github.com/audaspace/audaspace
Author: Jörg Müller
Author-email: nexyon@gmail.com
License: Apache License 2.0
Dynamic: author
Dynamic: author-email
Dynamic: description
Dynamic: description-content-type
Dynamic: home-page
Dynamic: license
Dynamic: summary
